[{"model": "auth.user", "pk": 1, "fields": {"password": "pbkdf2_sha256$260000$gokdjtwrFdTqmNRcqeg3Wy$pSuj4Fj+b9aVyh7J/M/HP08Ud7lxNhcUSEFuJeoK0fc=", "last_login": "2022-11-12T00:56:46.404Z", "is_superuser": true, "username": "admin", "first_name": "", "last_name": "", "email": "", "is_staff": true, "is_active": true, "date_joined": "2022-10-22T08:42:59.865Z", "groups": [], "user_permissions": []}}, {"model": "auth.user", "pk": 2, "fields": {"password": "pbkdf2_sha256$260000$R7D75d2DkYNvD4BWTqjZT1$XXym/WyyoE6s8inVkGocAJKGtFCddRMumR/v7Fmpbaw=", "last_login": "2022-11-11T13:22:28.786Z", "is_superuser": false, "username": "bolg", "first_name": "", "last_name": "", "email": "", "is_staff": false, "is_active": true, "date_joined": "2022-10-22T14:13:58.877Z", "groups": [], "user_permissions": []}}, {"model": "auth.user", "pk": 3, "fields": {"password": "!5YXk2yiQc18ArhVAPoh1OdP1QpKw8jdYSq96j4D8", "last_login": "2022-11-12T00:52:31.424Z", "is_superuser": false, "username": "john", "first_name": "John", "last_name": "Rearden", "email": "", "is_staff": false, "is_active": true, "date_joined": "2022-10-22T14:23:10.999Z", "groups": [], "user_permissions": []}}, {"model": "auth.user", "pk": 4, "fields": {"password": "pbkdf2_sha256$260000$nq7nOEc8zqJIIGUoxoLv5V$v7BkIk/FOIi1eStYocdTxLKedxRnN/BKSx2a0aEABoE=", "last_login": "2022-11-09T08:24:41.193Z", "is_superuser": false, "username": "monkey", "first_name": "", "last_name": "", "email": "", "is_staff": false, "is_active": true, "date_joined": "2022-11-09T08:24:41.051Z", "groups": [], "user_permissions": []}}, {"model": "auth.user", "pk": 5, "fields": {"password": "pbkdf2_sha256$260000$saj9ZXlteqXGDCB5Crq6y7$N8C/9mBrAtOyKwQnCwSgrynnmZsqGzXS8TeZy/6joFo=", "last_login": "2022-11-11T10:08:50.107Z", "is_superuser": false, "username": "Chewbacca", "first_name": "", "last_name": "", "email": "", "is_staff": false, "is_active": true, "date_joined": "2022-11-11T10:08:49.969Z", "groups": [], "user_permissions": []}}, {"model": "auth.user", "pk": 6, "fields": {"password": "pbkdf2_sha256$260000$nMiwIIZIptWNRuBqRA3v9D$o+eSl95nr3b69soJnkHYqbP2+31do3yL+0TW2qvI9xo=", "last_login": "2022-11-11T10:55:53.792Z", "is_superuser": false, "username": "alksdjfajsdkf", "first_name": "", "last_name": "", "email": "", "is_staff": false, "is_active": true, "date_joined": "2022-11-11T10:55:53.519Z", "groups": [], "user_permissions": []}}]